trackeval/__init__.py
trackeval/_timing.py
trackeval/eval.py
trackeval/plotting.py
trackeval/utils.py
trackeval/baselines/__init__.py
trackeval/baselines/baseline_utils.py
trackeval/baselines/non_overlap.py
trackeval/baselines/pascal_colormap.py
trackeval/baselines/stp.py
trackeval/baselines/thresholder.py
trackeval/baselines/vizualize.py
trackeval/datasets/__init__.py
trackeval/datasets/_base_dataset.py
trackeval/datasets/bdd100k.py
trackeval/datasets/burst.py
trackeval/datasets/burst_ow.py
trackeval/datasets/davis.py
trackeval/datasets/head_tracking_challenge.py
trackeval/datasets/kitti_2d_box.py
trackeval/datasets/kitti_mots.py
trackeval/datasets/mot_challenge_2d_box.py
trackeval/datasets/mots_challenge.py
trackeval/datasets/person_path_22.py
trackeval/datasets/rob_mots.py
trackeval/datasets/rob_mots_classmap.py
trackeval/datasets/run_rob_mots.py
trackeval/datasets/soccernet_gs.py
trackeval/datasets/tao.py
trackeval/datasets/tao_ow.py
trackeval/datasets/youtube_vis.py
trackeval/datasets/burst_helpers/__init__.py
trackeval/datasets/burst_helpers/burst_base.py
trackeval/datasets/burst_helpers/burst_ow_base.py
trackeval/datasets/burst_helpers/convert_burst_format_to_tao_format.py
trackeval/datasets/burst_helpers/format_converter.py
trackeval/metrics/__init__.py
trackeval/metrics/_base_metric.py
trackeval/metrics/clear.py
trackeval/metrics/count.py
trackeval/metrics/hota.py
trackeval/metrics/identity.py
trackeval/metrics/ideucl.py
trackeval/metrics/j_and_f.py
trackeval/metrics/track_map.py
trackeval/metrics/vace.py
sn_trackeval-0.4.0.dist-info/LICENSE
sn_trackeval-0.4.0.dist-info/METADATA
sn_trackeval-0.4.0.dist-info/WHEEL
sn_trackeval-0.4.0.dist-info/top_level.txt
sn_trackeval-0.4.0.dist-info/RECORD
