Metadata-Version: 2.1
Name: sn-trackeval
Version: 0.4.0
Summary: Code for evaluating object tracking
Author-email: Vladimir Somers <somers.vladimir@gmail.com>, Jonathon Luiten <jonoluiten@gmail.com>, Arne Hoffhues <no-email@example.com>, Victor Joos <victorjoosdtb@gmail.com>
License: MIT License
Project-URL: homepage, https://github.com/SoccerNet/sn-trackeval
Classifier: Programming Language :: Python :: 3
Classifier: Programming Language :: Python :: 3 :: Only
Classifier: License :: OSI Approved :: MIT License
Classifier: Operating System :: OS Independent
Classifier: Topic :: Scientific/Engineering
License-File: LICENSE
Requires-Dist: numpy
Requires-Dist: scipy
Requires-Dist: pycocotools
Requires-Dist: matplotlib
Requires-Dist: opencv-python
Requires-Dist: scikit-image
Requires-Dist: pytest
Requires-Dist: Pillow
Requires-Dist: tqdm
Requires-Dist: tabulate
